{
  "key": "fields_5659945",
  "title": "Coordinate Progetti - Campi Personalizzati",
  "fields": [
    {
      "key": "field_coordinate",
      "label": "Coordinate",
      "name": "coordinate",
      "aria-label": "",
      "type": "textarea",
      "instructions": "",
      "required": 0,
      "conditional_logic": 0,
      "wrapper": {
        "width": "",
        "class": "",
        "id": ""
      },
      "default_value": "",
      "maxlength": "",
      "placeholder": "",
      "prepend": "",
      "append": "",
      "new_lines": "",
      "rows": 4
    }
  ],
  "location": [
    [
      {
        "param": "post_type",
        "operator": "==",
        "value": "post_type_5659945"
      }
    ]
  ],
  "menu_order": 0,
  "position": "normal",
  "style": "default",
  "label_placement": "top",
  "instruction_placement": "label",
  "hide_on_screen": "",
  "active": true,
  "description": "\u003C?xml version=\u00271.0\u0027 encoding=\u0027UTF-8\u0027?\u003E\u003Croot available-locales=\u0022it_IT\u0022 default-locale=\u0022it_IT\u0022\u003E\u003CDescription language-id=\u0022it_IT\u0022\u003ECoordinate Progetti\u003C/Description\u003E\u003C/root\u003E",
  "show_in_rest": 1,
  "display_title": ""
}